h5pywrappers/__init__.py
h5pywrappers/attr.py
h5pywrappers/dataset.py
h5pywrappers/datasubset.py
h5pywrappers/group.py
h5pywrappers/obj.py
h5pywrappers/scalar.py
h5pywrappers/version.py
h5pywrappers/json/__init__.py
h5pywrappers/json/document.py
h5pywrappers-0.0.5.dist-info/licenses/LICENSE
h5pywrappers-0.0.5.dist-info/METADATA
h5pywrappers-0.0.5.dist-info/WHEEL
h5pywrappers-0.0.5.dist-info/top_level.txt
h5pywrappers-0.0.5.dist-info/RECORD
