Metadata-Version: 2.4
Name: h5pywrappers
Version: 0.0.5
Summary: Contains several functions used to facilitate loading data from and saving data to HDF5 files. These functions are wrappers that call functions from the library ``h5py``.
Author-email: Matthew Fitzpatrick <matthew.rc.fitzpatrick@gmail.com>
Project-URL: Homepage, https://mrfitzpa.github.io/h5pywrappers
Project-URL: Repository, https://github.com/mrfitzpa/h5pywrappers
Keywords: HDF5,h5py
Classifier: License :: OSI Approved :: GNU General Public License v3 (GPLv3)
Classifier: Development Status :: 5 - Production/Stable
Classifier: Intended Audience :: Developers
Classifier: Programming Language :: Python
Classifier: Programming Language :: Python :: 3
Classifier: Programming Language :: Python :: 3.8
Classifier: Programming Language :: Python :: 3.9
Classifier: Programming Language :: Python :: 3.10
Classifier: Programming Language :: Python :: 3.11
Classifier: Programming Language :: Python :: 3.12
Classifier: Operating System :: OS Independent
Classifier: Natural Language :: English
Requires-Python: >=3.8
License-File: LICENSE
Requires-Dist: czekitout>=1.0.0
Requires-Dist: fancytypes>=1.0.0
Requires-Dist: h5py
Provides-Extra: tests
Requires-Dist: pytest-cov; extra == "tests"
Provides-Extra: examples
Requires-Dist: jupyter; extra == "examples"
Provides-Extra: docs
Requires-Dist: sphinx; extra == "docs"
Requires-Dist: sphinx_rtd_theme; extra == "docs"
Requires-Dist: sphinx-autodoc-typehints; extra == "docs"
Requires-Dist: numpydoc; extra == "docs"
Requires-Dist: docutils; extra == "docs"
Provides-Extra: all
Requires-Dist: h5pywrappers[docs,examples,tests]; extra == "all"
Dynamic: license-file
